nai3api.py
nai3api-0.0.1.1.dist-info/WHEEL
nai3api-0.0.1.1.dist-info/METADATA
nai3api-0.0.1.1.dist-info/RECORD
